country_emoji/__init__.py
country_emoji/data.py
country_emoji-0.0.1.dist-info/METADATA
country_emoji-0.0.1.dist-info/WHEEL
country_emoji-0.0.1.dist-info/licenses/LICENSE
country_emoji-0.0.1.dist-info/RECORD
